solverarena/__init__.py
solverarena/core.py
solverarena/utils.py
solverarena/solvers/__init__.py
solverarena/solvers/cbc_solver.py
solverarena/solvers/copt_solver.py
solverarena/solvers/glop_solver.py
solverarena/solvers/gurobi_solver.py
solverarena/solvers/highs_solver.py
solverarena/solvers/pdlp_solver.py
solverarena/solvers/scip_solver.py
solverarena/solvers/solver.py
solverarena/solvers/solver_factory.py
solverarena/solvers/utils.py
solverarena-0.2.7.dist-info/licenses/LICENSE.txt
solverarena-0.2.7.dist-info/METADATA
solverarena-0.2.7.dist-info/WHEEL
solverarena-0.2.7.dist-info/top_level.txt
solverarena-0.2.7.dist-info/RECORD
