Metadata-Version: 2.4
Name: solverarena
Version: 0.2.7
Summary: A library to run and compare optimization models
Author-email: Javier Berga García <pataq21@gmail.com>
License: MIT
Project-URL: Homepage, https://github.com/pataq21/SolverArena
Project-URL: Repository, https://github.com/pataq21/SolverArena
Requires-Python: >=3.12
License-File: LICENSE.txt
Requires-Dist: build>=1.2.2.post1
Requires-Dist: coptpy>=7.2.7
Requires-Dist: memory-profiler
Requires-Dist: pulp>=3.1.1
Provides-Extra: highs
Requires-Dist: highspy; extra == "highs"
Provides-Extra: gurobi
Requires-Dist: gurobipy; extra == "gurobi"
Provides-Extra: copt
Requires-Dist: coptpy; extra == "copt"
Provides-Extra: scip
Requires-Dist: pyscipopt; extra == "scip"
Provides-Extra: ortools
Requires-Dist: ortools; extra == "ortools"
Provides-Extra: all-solvers
Requires-Dist: solverarena[highs]; extra == "all-solvers"
Requires-Dist: solverarena[gurobi]; extra == "all-solvers"
Requires-Dist: solverarena[scip]; extra == "all-solvers"
Requires-Dist: solverarena[ortools]; extra == "all-solvers"
Requires-Dist: solverarena[copt]; extra == "all-solvers"
Provides-Extra: dev
Requires-Dist: pytest; extra == "dev"
Requires-Dist: twine; extra == "dev"
Requires-Dist: highspy; extra == "dev"
Requires-Dist: gurobipy; extra == "dev"
Requires-Dist: pyscipopt; extra == "dev"
Requires-Dist: ortools; extra == "dev"
Requires-Dist: pytest-mock>=3.14.0; extra == "dev"
Dynamic: license-file
